{"player":3,"street":0,"children":3,"sequence":[{"player":0,"type":"F","amount":0,"street":0},{"player":1,"type":"R","amount":250000,"street":0},{"player":2,"type":"F","amount":0,"street":0},{"player":3,"type":"R","amount":1000000,"street":0},{"player":4,"type":"F","amount":0,"street":0},{"player":5,"type":"F","amount":0,"street":0},{"player":6,"type":"F","amount":0,"street":0},{"player":7,"type":"F","amount":0,"street":0},{"player":1,"type":"R","amount":2500000,"street":0}],"actions":[{"type":"F","amount":0},{"type":"C","amount":1500000},{"type":"R","amount":10000000,"node":1215}],"hands":{"22":{"weight":0.0,"played":[1.0,0.0,0.0],"evs":[0.0,-0.05119,-0.32779]},"32o":{"weight":0.0,"played":[1.0,0.0,0.0],"evs":[0.0,-0.5238,-1.55953]},"42o":{"weight":0.0,"played":[1.0,0.0,0.0],"evs":[0.0,-0.53195,-1.5605]},"52o":{"weight":0.0,"played":[1.0,0.0,0.0],"evs":[0.0,-0.53028,-1.51121]},"62o":{"weight":0.0,"played":[1.0,0.0,0.0],"evs":[0.0,-0.60702,-1.61058]},"72o":{"weight":0.0,"played":[1.0,0.0,0.0],"evs":[0.0,-0.70435,-1.81853]},"82o":{"weight":0.0,"played":[1.0,0.0,0.0],"evs":[0.0,-0.66621,-1.78255]},"92o":{"weight":0.0,"played":[1.0,0.0,0.0],"evs":[0.0,-0.6594,-1.83855]},"T2o":{"weight":0.0,"played":[1.0,0.0,0.0],"evs":[0.0,-0.67371,-1.86238]},"J2o":{"weight":0.0,"played":[1.0,0.0,0.0],"evs":[0.0,-0.63729,-1.7975]},"Q2o":{"weight":0.0,"played":[1.0,0.0,0.0],"evs":[0.0,-0.55715,-1.75985]},"K2o":{"weight":0.0,"played":[1.0,0.0,0.0],"evs":[0.0,-0.52189,-1.54653]},"A2o":{"weight":0.0,"played":[1.0,0.0,0.0],"evs":[0.0,-0.39034,-0.88267]},"32s":{"weight":0.0,"played":[1.0,0.0,0.0],"evs":[0.0,-0.19633,-1.02594]},"33":{"weight":0.0,"played":[1.0,0.0,0.0],"evs":[0.0,-0.02981,-0.26624]},"43o":{"weight":0.0,"played":[1.0,0.0,0.0],"evs":[0.0,-0.42861,-1.35105]},"53o":{"weight":0.0,"played":[1.0,0.0,0.0],"evs":[0.0,-0.41865,-1.29644]},"63o":{"weight":0.0,"played":[1.0,0.0,0.0],"evs":[0.0,-0.49955,-1.39689]},"73o":{"weight":0.0,"played":[1.0,0.0,0.0],"evs":[0.0,-0.62304,-1.604]},"83o":{"weight":0.0,"played":[1.0,0.0,0.0],"evs":[0.0,-0.68213,-1.78012]},"93o":{"weight":0.0,"played":[1.0,0.0,0.0],"evs":[0.0,-0.65373,-1.78517]},"T3o":{"weight":0.0,"played":[1.0,0.0,0.0],"evs":[0.0,-0.6702,-1.80841]},"J3o":{"weight":0.0,"played":[1.0,0.0,0.0],"evs":[0.0,-0.6281,-1.74799]},"Q3o":{"weight":0.0,"played":[1.0,0.0,0.0],"evs":[0.0,-0.54877,-1.7008]},"K3o":{"weight":0.0,"played":[1.0,0.0,0.0],"evs":[0.0,-0.5172,-1.4914]},"A3o":{"weight":0.0,"played":[1.0,0.0,0.0],"evs":[0.0,-0.37433,-0.82388]},"42s":{"weight":0.0,"played":[1.0,0.0,0.0],"evs":[0.0,-0.20137,-1.03421]},"43s":{"weight":0.0,"played":[1.0,0.0,0.0],"evs":[0.0,-0.0939,-0.83058]},"44":{"weight":0.0,"played":[0.9996,4.0E-4,0.0],"evs":[0.0,-0.02603,-0.29587]},"54o":{"weight":0.0,"played":[1.0,0.0,0.0],"evs":[0.0,-0.35408,-1.13546]},"64o":{"weight":0.0,"played":[1.0,0.0,0.0],"evs":[0.0,-0.41483,-1.23661]},"74o":{"weight":0.0,"played":[1.0,0.0,0.0],"evs":[0.0,-0.53937,-1.44518]},"84o":{"weight":0.0,"played":[1.0,0.0,0.0],"evs":[0.0,-0.62628,-1.62933]},"94o":{"weight":0.0,"played":[1.0,0.0,0.0],"evs":[0.0,-0.69179,-1.84667]},"T4o":{"weight":0.0,"played":[1.0,0.0,0.0],"evs":[0.0,-0.70014,-1.81342]},"J4o":{"weight":0.0,"played":[1.0,0.0,0.0],"evs":[0.0,-0.64661,-1.74984]},"Q4o":{"weight":0.0,"played":[1.0,0.0,0.0],"evs":[0.0,-0.5725,-1.70859]},"K4o":{"weight":0.0,"played":[1.0,0.0,0.0],"evs":[0.0,-0.55525,-1.50499]},"A4o":{"weight":0.0,"played":[1.0,0.0,0.0],"evs":[0.0,-0.38374,-0.83943]},"52s":{"weight":0.0,"played":[1.0,0.0,0.0],"evs":[0.0,-0.19944,-0.98336]},"53s":{"weight":0.0,"played":[1.0,0.0,0.0],"evs":[0.0,-0.07948,-0.77034]},"54s":{"weight":0.2009,"played":[0.4711,0.5289,0.0],"evs":[0.0,-0.00157,-0.62399]},"55":{"weight":0.0524,"played":[0.2689,0.7311,0.0],"evs":[0.0,0.00295,-0.22708]},"65o":{"weight":0.0,"played":[1.0,0.0,0.0],"evs":[0.0,-0.33822,-1.02185]},"75o":{"weight":0.0,"played":[1.0,0.0,0.0],"evs":[0.0,-0.44118,-1.22135]},"85o":{"weight":0.0,"played":[1.0,0.0,0.0],"evs":[0.0,-0.527,-1.40428]},"95o":{"weight":0.0,"played":[1.0,0.0,0.0],"evs":[0.0,-0.61982,-1.62293]},"T5o":{"weight":0.0,"played":[1.0,0.0,0.0],"evs":[0.0,-0.7135,-1.80486]},"J5o":{"weight":0.0,"played":[1.0,0.0,0.0],"evs":[0.0,-0.6592,-1.69494]},"Q5o":{"weight":0.0,"played":[1.0,0.0,0.0],"evs":[0.0,-0.57385,-1.65483]},"K5o":{"weight":0.0,"played":[1.0,0.0,0.0],"evs":[0.0,-0.56785,-1.45287]},"A5o":{"weight":0.0,"played":[1.0,0.0,0.0],"evs":[0.0,-0.38346,-0.78621]},"62s":{"weight":0.0,"played":[1.0,0.0,0.0],"evs":[0.0,-0.28285,-1.0752]},"63s":{"weight":0.0,"played":[1.0,0.0,0.0],"evs":[0.0,-0.17278,-0.8773]},"64s":{"weight":0.0,"played":[1.0,0.0,0.0],"evs":[0.0,-0.07313,-0.73099]},"65s":{"weight":0.1896,"played":[0.2956,0.7044,0.0],"evs":[0.0,0.00175,-0.52641]},"66":{"weight":0.1282,"played":[0.0,1.0,0.0],"evs":[0.0,0.04284,-0.10485]},"76o":{"weight":0.0,"played":[1.0,0.0,0.0],"evs":[0.0,-0.34896,-0.99368]},"86o":{"weight":0.0,"played":[1.0,0.0,0.0],"evs":[0.0,-0.40244,-1.1701]},"96o":{"weight":0.0,"played":[1.0,0.0,0.0],"evs":[0.0,-0.48497,-1.38695]},"T6o":{"weight":0.0,"played":[1.0,0.0,0.0],"evs":[0.0,-0.61557,-1.56496]},"J6o":{"weight":0.0,"played":[1.0,0.0,0.0],"evs":[0.0,-0.63762,-1.65601]},"Q6o":{"weight":0.0,"played":[1.0,0.0,0.0],"evs":[0.0,-0.54303,-1.56939]},"K6o":{"weight":0.0,"played":[1.0,0.0,0.0],"evs":[0.0,-0.51945,-1.3517]},"A6o":{"weight":0.0,"played":[1.0,0.0,0.0],"evs":[0.0,-0.44153,-0.90078]},"72s":{"weight":0.0,"played":[1.0,0.0,0.0],"evs":[0.0,-0.37467,-1.26112]},"73s":{"weight":0.0,"played":[1.0,0.0,0.0],"evs":[0.0,-0.29071,-1.06078]},"74s":{"weight":0.0,"played":[1.0,0.0,0.0],"evs":[0.0,-0.1992,-0.91573]},"75s":{"weight":0.0,"played":[1.0,0.0,0.0],"evs":[0.0,-0.09585,-0.70668]},"76s":{"weight":0.1313,"played":[0.0294,0.9706,0.0],"evs":[0.0,0.0029,-0.48896]},"77":{"weight":0.0902,"played":[0.0,1.0,0.0],"evs":[0.0,0.01736,-0.13651]},"87o":{"weight":0.0,"played":[1.0,0.0,0.0],"evs":[0.0,-0.33319,-1.04558]},"97o":{"weight":0.0,"played":[1.0,0.0,0.0],"evs":[0.0,-0.39837,-1.26463]},"T7o":{"weight":0.0,"played":[1.0,0.0,0.0],"evs":[0.0,-0.50233,-1.437]},"J7o":{"weight":0.0,"played":[1.0,0.0,0.0],"evs":[0.0,-0.57787,-1.52757]},"Q7o":{"weight":0.0,"played":[1.0,0.0,0.0],"evs":[0.0,-0.56393,-1.65132]},"K7o":{"weight":0.0,"played":[1.0,0.0,0.0],"evs":[0.0,-0.5334,-1.37761]},"A7o":{"weight":0.0,"played":[1.0,0.0,0.0],"evs":[0.0,-0.41791,-0.89044]},"82s":{"weight":0.0,"played":[1.0,0.0,0.0],"evs":[0.0,-0.34357,-1.23886]},"83s":{"weight":0.0,"played":[1.0,0.0,0.0],"evs":[0.0,-0.35494,-1.22973]},"84s":{"weight":0.0,"played":[1.0,0.0,0.0],"evs":[0.0,-0.29714,-1.09101]},"85s":{"weight":0.0,"played":[1.0,0.0,0.0],"evs":[0.0,-0.18407,-0.8805]},"86s":{"weight":0.0,"played":[1.0,0.0,0.0],"evs":[0.0,-0.06695,-0.66025]},"87s":{"weight":0.1537,"played":[0.0138,0.9862,0.0],"evs":[0.0,0.00969,-0.54397]},"88":{"weight":0.0102,"played":[0.0,1.0,0.0],"evs":[0.0,0.05072,-0.12588]},"98o":{"weight":0.0,"played":[1.0,0.0,0.0],"evs":[0.0,-0.32425,-1.18306]},"T8o":{"weight":0.0,"played":[1.0,0.0,0.0],"evs":[0.0,-0.38248,-1.26168]},"J8o":{"weight":0.0,"played":[1.0,0.0,0.0],"evs":[0.0,-0.45439,-1.35231]},"Q8o":{"weight":0.0,"played":[1.0,0.0,0.0],"evs":[0.0,-0.47505,-1.47905]},"K8o":{"weight":0.0,"played":[1.0,0.0,0.0],"evs":[0.0,-0.52293,-1.4104]},"A8o":{"weight":0.0,"played":[1.0,0.0,0.0],"evs":[0.0,-0.40327,-0.9081]},"92s":{"weight":0.0,"played":[1.0,0.0,0.0],"evs":[0.0,-0.33894,-1.28827]},"93s":{"weight":0.0,"played":[1.0,0.0,0.0],"evs":[0.0,-0.3327,-1.2419]},"94s":{"weight":0.0,"played":[1.0,0.0,0.0],"evs":[0.0,-0.36883,-1.29635]},"95s":{"weight":0.0,"played":[1.0,0.0,0.0],"evs":[0.0,-0.29152,-1.08919]},"96s":{"weight":0.0,"played":[1.0,0.0,0.0],"evs":[0.0,-0.15121,-0.8626]},"97s":{"weight":0.0,"played":[1.0,0.0,0.0],"evs":[0.0,-0.06416,-0.7535]},"98s":{"weight":0.0,"played":[1.0E-4,0.9999,0.0],"evs":[0.0,0.01454,-0.671]},"99":{"weight":0.0391,"played":[0.0,1.0,0.0],"evs":[0.0,0.06844,-0.18543]},"T9o":{"weight":0.0,"played":[1.0,0.0,0.0],"evs":[0.0,-0.34965,-1.17529]},"J9o":{"weight":0.0,"played":[1.0,0.0,0.0],"evs":[0.0,-0.37806,-1.25746]},"Q9o":{"weight":0.0,"played":[1.0,0.0,0.0],"evs":[0.0,-0.42891,-1.39379]},"K9o":{"weight":0.0,"played":[1.0,0.0,0.0],"evs":[0.0,-0.49405,-1.35536]},"A9o":{"weight":0.0,"played":[1.0,0.0,0.0],"evs":[0.0,-0.38651,-0.96956]},"T2s":{"weight":0.0,"played":[1.0,0.0,0.0],"evs":[0.0,-0.35078,-1.30863]},"T3s":{"weight":0.0,"played":[1.0,0.0,0.0],"evs":[0.0,-0.34184,-1.258]},"T4s":{"weight":0.0,"played":[1.0,0.0,0.0],"evs":[0.0,-0.36832,-1.2668]},"T5s":{"weight":0.0,"played":[1.0,0.0,0.0],"evs":[0.0,-0.38126,-1.25344]},"T6s":{"weight":0.0,"played":[1.0,0.0,0.0],"evs":[0.0,-0.27891,-1.0315]},"T7s":{"weight":0.0,"played":[1.0,0.0,0.0],"evs":[0.0,-0.16238,-0.91206]},"T8s":{"weight":0.093,"played":[1.0,0.0,0.0],"evs":[0.0,-0.04644,-0.75091]},"T9s":{"weight":0.2437,"played":[0.3537,0.6463,0.0],"evs":[0.0,-2.8E-4,-0.6621]},"TT":{"weight":0.1547,"played":[0.0,1.0,0.0],"evs":[0.0,0.10188,-0.04038]},"JTo":{"weight":0.0,"played":[1.0,0.0,0.0],"evs":[0.0,-0.31283,-1.15117]},"QTo":{"weight":0.0,"played":[1.0,0.0,0.0],"evs":[0.0,-0.34387,-1.29983]},"KTo":{"weight":0.0173,"played":[1.0,0.0,0.0],"evs":[0.0,-0.38418,-1.21808]},"ATo":{"weight":0.0996,"played":[1.0,0.0,0.0],"evs":[0.0,-0.31026,-0.88415]},"J2s":{"weight":0.0,"played":[1.0,0.0,0.0],"evs":[0.0,-0.30374,-1.23389]},"J3s":{"weight":0.0,"played":[1.0,0.0,0.0],"evs":[0.0,-0.29899,-1.18914]},"J4s":{"weight":0.0,"played":[1.0,0.0,0.0],"evs":[0.0,-0.31217,-1.19385]},"J5s":{"weight":0.0,"played":[1.0,0.0,0.0],"evs":[0.0,-0.32517,-1.14542]},"J6s":{"weight":0.0,"played":[1.0,0.0,0.0],"evs":[0.0,-0.3058,-1.11698]},"J7s":{"weight":0.0,"played":[1.0,0.0,0.0],"evs":[0.0,-0.23804,-0.98622]},"J8s":{"weight":0.0,"played":[1.0,0.0,0.0],"evs":[0.0,-0.11869,-0.82773]},"J9s":{"weight":0.0044,"played":[0.9999,1.0E-4,0.0],"evs":[0.0,-0.03361,-0.73455]},"JTs":{"weight":0.1313,"played":[0.0,1.0,0.0],"evs":[0.0,0.04102,-0.63893]},"JJ":{"weight":0.2027,"played":[0.0,0.872,0.128],"evs":[0.0,0.47401,0.46751]},"QJo":{"weight":0.0,"played":[1.0,0.0,0.0],"evs":[0.0,-0.33431,-1.24026]},"KJo":{"weight":0.0941,"played":[1.0,0.0,0.0],"evs":[0.0,-0.25716,-1.13632]},"AJo":{"weight":0.2111,"played":[1.0,0.0,0.0],"evs":[0.0,-0.15886,-0.79784]},"Q2s":{"weight":0.0,"played":[1.0,0.0,0.0],"evs":[0.0,-0.24719,-1.20627]},"Q3s":{"weight":0.0,"played":[1.0,0.0,0.0],"evs":[0.0,-0.23875,-1.14797]},"Q4s":{"weight":0.0,"played":[1.0,0.0,0.0],"evs":[0.0,-0.2558,-1.15443]},"Q5s":{"weight":0.0,"played":[1.0,0.0,0.0],"evs":[0.0,-0.26293,-1.1207]},"Q6s":{"weight":0.0,"played":[1.0,0.0,0.0],"evs":[0.0,-0.22599,-1.03295]},"Q7s":{"weight":0.0,"played":[1.0,0.0,0.0],"evs":[0.0,-0.25064,-1.1]},"Q8s":{"weight":0.0,"played":[1.0,0.0,0.0],"evs":[0.0,-0.15024,-0.94581]},"Q9s":{"weight":0.0039,"played":[1.0,0.0,0.0],"evs":[0.0,-0.09749,-0.85755]},"QTs":{"weight":0.1195,"played":[0.9769,0.0231,0.0],"evs":[0.0,-0.01014,-0.77436]},"QJs":{"weight":0.1906,"played":[0.2762,0.7238,0.0],"evs":[0.0,0.00207,-0.70772]},"QQ":{"weight":0.2419,"played":[0.0,1.0,0.0],"evs":[0.0,0.9039,0.83591]},"KQo":{"weight":0.4343,"played":[1.0,0.0,0.0],"evs":[0.0,-0.20983,-1.06314]},"AQo":{"weight":0.2017,"played":[0.7416,0.2584,0.0],"evs":[0.0,-3.9E-4,-0.67337]},"K2s":{"weight":0.0,"played":[1.0,0.0,0.0],"evs":[0.0,-0.2123,-0.99814]},"K3s":{"weight":0.0,"played":[1.0,0.0,0.0],"evs":[0.0,-0.20844,-0.94286]},"K4s":{"weight":0.0215,"played":[1.0,0.0,0.0],"evs":[0.0,-0.25205,-0.95708]},"K5s":{"weight":0.2013,"played":[1.0,0.0,0.0],"evs":[0.0,-0.24123,-0.90458]},"K6s":{"weight":0.0,"played":[1.0,0.0,0.0],"evs":[0.0,-0.20765,-0.8175]},"K7s":{"weight":0.1985,"played":[1.0,0.0,0.0],"evs":[0.0,-0.22264,-0.84309]},"K8s":{"weight":0.2857,"played":[1.0,0.0,0.0],"evs":[0.0,-0.20232,-0.85932]},"K9s":{"weight":0.3538,"played":[1.0,0.0,0.0],"evs":[0.0,-0.17762,-0.81741]},"KTs":{"weight":0.1209,"played":[1.0,0.0,0.0],"evs":[0.0,-0.03087,-0.64025]},"KJs":{"weight":0.1179,"played":[0.0,1.0,0.0],"evs":[0.0,0.10696,-0.49056]},"KQs":{"weight":0.2045,"played":[0.0,1.0,0.0],"evs":[0.0,0.10995,-0.52392]},"KK":{"weight":0.656,"played":[0.0,0.0,1.0],"evs":[0.0,2.54439,2.57361]},"AKo":{"weight":0.6169,"played":[0.0,0.1929,0.8071],"evs":[0.0,0.9523,0.95329]},"A2s":{"weight":0.7325,"played":[1.0,0.0,0.0],"evs":[0.0,-0.01838,-0.34862]},"A3s":{"weight":0.8128,"played":[0.9802,0.0198,0.0],"evs":[0.0,-0.00399,-0.30109]},"A4s":{"weight":0.1734,"played":[0.9555,0.0445,0.0],"evs":[0.0,-0.00451,-0.24786]},"A5s":{"weight":0.321,"played":[0.2254,0.7746,0.0],"evs":[0.0,8.6E-4,-0.19217]},"A6s":{"weight":0.4588,"played":[1.0,0.0,0.0],"evs":[0.0,-0.07449,-0.37149]},"A7s":{"weight":0.3938,"played":[0.9997,3.0E-4,0.0],"evs":[0.0,-0.04261,-0.32768]},"A8s":{"weight":0.2605,"played":[0.9999,1.0E-4,0.0],"evs":[0.0,-0.02127,-0.35694]},"A9s":{"weight":0.0522,"played":[0.1087,0.8913,0.0],"evs":[0.0,0.00161,-0.39661]},"ATs":{"weight":0.2009,"played":[0.0,1.0,0.0],"evs":[0.0,0.10764,-0.24057]},"AJs":{"weight":0.3047,"played":[0.0,1.0,0.0],"evs":[0.0,0.25285,-0.2008]},"AQs":{"weight":0.0924,"played":[0.0,1.0,0.0],"evs":[0.0,0.43464,-0.1805]},"AKs":{"weight":0.4954,"played":[0.0,0.1506,0.8494],"evs":[0.0,1.34544,1.34893]},"AA":{"weight":1.0,"played":[0.0,0.653,0.347],"evs":[0.0,6.75674,6.7556]}}}