{"player":3,"street":0,"children":3,"sequence":[{"player":0,"type":"R","amount":250000,"street":0},{"player":1,"type":"F","amount":0,"street":0},{"player":2,"type":"R","amount":1000000,"street":0}],"actions":[{"type":"F","amount":0,"node":456},{"type":"R","amount":2000000,"node":427},{"type":"R","amount":10000000}],"hands":{"22":{"weight":1.0,"played":[1.0,0.0,0.0],"evs":[0.0,-0.1438,-0.95841]},"32o":{"weight":1.0,"played":[1.0,0.0,0.0],"evs":[0.0,-0.25085,-1.98978]},"42o":{"weight":1.0,"played":[1.0,0.0,0.0],"evs":[0.0,-0.23241,-1.93822]},"52o":{"weight":1.0,"played":[1.0,0.0,0.0],"evs":[0.0,-0.22876,-1.89177]},"62o":{"weight":1.0,"played":[1.0,0.0,0.0],"evs":[0.0,-0.23721,-1.98252]},"72o":{"weight":1.0,"played":[1.0,0.0,0.0],"evs":[0.0,-0.27927,-2.16866]},"82o":{"weight":1.0,"played":[1.0,0.0,0.0],"evs":[0.0,-0.27074,-2.12868]},"92o":{"weight":1.0,"played":[1.0,0.0,0.0],"evs":[0.0,-0.27185,-2.15948]},"T2o":{"weight":1.0,"played":[1.0,0.0,0.0],"evs":[0.0,-0.29058,-2.16531]},"J2o":{"weight":1.0,"played":[1.0,0.0,0.0],"evs":[0.0,-0.29372,-2.17678]},"Q2o":{"weight":1.0,"played":[1.0,0.0,0.0],"evs":[0.0,-0.31287,-2.20433]},"K2o":{"weight":1.0,"played":[1.0,0.0,0.0],"evs":[0.0,-0.18696,-2.02647]},"A2o":{"weight":1.0,"played":[1.0,0.0,0.0],"evs":[0.0,-0.14579,-1.40313]},"32s":{"weight":1.0,"played":[1.0,0.0,0.0],"evs":[0.0,-0.16222,-1.57122]},"33":{"weight":1.0,"played":[1.0,0.0,0.0],"evs":[0.0,-0.13538,-0.92158]},"43o":{"weight":1.0,"played":[1.0,0.0,0.0],"evs":[0.0,-0.20334,-1.78239]},"53o":{"weight":1.0,"played":[1.0,0.0,0.0],"evs":[0.0,-0.19406,-1.72837]},"63o":{"weight":1.0,"played":[1.0,0.0,0.0],"evs":[0.0,-0.2022,-1.81978]},"73o":{"weight":1.0,"played":[1.0,0.0,0.0],"evs":[0.0,-0.2535,-2.01052]},"83o":{"weight":1.0,"played":[1.0,0.0,0.0],"evs":[0.0,-0.27908,-2.14831]},"93o":{"weight":1.0,"played":[1.0,0.0,0.0],"evs":[0.0,-0.27535,-2.13866]},"T3o":{"weight":1.0,"played":[1.0,0.0,0.0],"evs":[0.0,-0.29327,-2.13989]},"J3o":{"weight":1.0,"played":[1.0,0.0,0.0],"evs":[0.0,-0.29671,-2.15539]},"Q3o":{"weight":1.0,"played":[1.0,0.0,0.0],"evs":[0.0,-0.31431,-2.17905]},"K3o":{"weight":1.0,"played":[1.0,0.0,0.0],"evs":[0.0,-0.1908,-2.00912]},"A3o":{"weight":1.0,"played":[1.0,0.0,0.0],"evs":[0.0,-0.14333,-1.38373]},"42s":{"weight":1.0,"played":[1.0,0.0,0.0],"evs":[0.0,-0.14283,-1.52516]},"43s":{"weight":1.0,"played":[1.0,0.0,0.0],"evs":[0.0,-0.11191,-1.36452]},"44":{"weight":1.0,"played":[1.0,0.0,0.0],"evs":[0.0,-0.10356,-0.84421]},"54o":{"weight":1.0,"played":[1.0,0.0,0.0],"evs":[0.0,-0.14217,-1.54501]},"64o":{"weight":1.0,"played":[1.0,0.0,0.0],"evs":[0.0,-0.14829,-1.63165]},"74o":{"weight":1.0,"played":[1.0,0.0,0.0],"evs":[0.0,-0.20168,-1.83028]},"84o":{"weight":1.0,"played":[1.0,0.0,0.0],"evs":[0.0,-0.23035,-1.96358]},"94o":{"weight":1.0,"played":[1.0,0.0,0.0],"evs":[0.0,-0.26625,-2.12409]},"T4o":{"weight":1.0,"played":[1.0,0.0,0.0],"evs":[0.0,-0.27758,-2.08224]},"J4o":{"weight":1.0,"played":[1.0,0.0,0.0],"evs":[0.0,-0.284,-2.09877]},"Q4o":{"weight":1.0,"played":[1.0,0.0,0.0],"evs":[0.0,-0.29898,-2.13022]},"K4o":{"weight":1.0,"played":[1.0,0.0,0.0],"evs":[0.0,-0.17193,-1.952]},"A4o":{"weight":1.0,"played":[1.0,0.0,0.0],"evs":[0.0,-0.12155,-1.33991]},"52s":{"weight":1.0,"played":[1.0,0.0,0.0],"evs":[0.0,-0.13654,-1.46414]},"53s":{"weight":1.0,"played":[1.0,0.0,0.0],"evs":[0.0,-0.10607,-1.32514]},"54s":{"weight":1.0,"played":[1.0,0.0,0.0],"evs":[0.0,-0.05325,-1.14895]},"55":{"weight":1.0,"played":[1.0,0.0,0.0],"evs":[0.0,-0.07995,-0.79117]},"65o":{"weight":1.0,"played":[1.0,0.0,0.0],"evs":[0.0,-0.10893,-1.46341]},"75o":{"weight":1.0,"played":[1.0,0.0,0.0],"evs":[0.0,-0.15518,-1.65063]},"85o":{"weight":1.0,"played":[1.0,0.0,0.0],"evs":[0.0,-0.1859,-1.79031]},"95o":{"weight":1.0,"played":[1.0,0.0,0.0],"evs":[0.0,-0.22582,-1.96019]},"T5o":{"weight":1.0,"played":[1.0,0.0,0.0],"evs":[0.0,-0.27706,-2.09529]},"J5o":{"weight":1.0,"played":[1.0,0.0,0.0],"evs":[0.0,-0.27822,-2.0657]},"Q5o":{"weight":1.0,"played":[1.0,0.0,0.0],"evs":[0.0,-0.29717,-2.09615]},"K5o":{"weight":1.0,"played":[1.0,0.0,0.0],"evs":[0.0,-0.16402,-1.91738]},"A5o":{"weight":1.0,"played":[1.0,0.0,0.0],"evs":[0.0,-0.10896,-1.29831]},"62s":{"weight":1.0,"played":[1.0,0.0,0.0],"evs":[0.0,-0.1459,-1.56162]},"63s":{"weight":1.0,"played":[1.0,0.0,0.0],"evs":[0.0,-0.10578,-1.40613]},"64s":{"weight":1.0,"played":[1.0,0.0,0.0],"evs":[0.0,-0.05711,-1.23383]},"65s":{"weight":1.0,"played":[0.997,0.003,0.0],"evs":[0.0,-0.01342,-1.05929]},"66":{"weight":1.0,"played":[1.0,0.0,0.0],"evs":[0.0,-0.02948,-0.70893]},"76o":{"weight":1.0,"played":[1.0,0.0,0.0],"evs":[0.0,-0.10775,-1.48185]},"86o":{"weight":1.0,"played":[1.0,0.0,0.0],"evs":[0.0,-0.134,-1.62049]},"96o":{"weight":1.0,"played":[1.0,0.0,0.0],"evs":[0.0,-0.16833,-1.78908]},"T6o":{"weight":1.0,"played":[1.0,0.0,0.0],"evs":[0.0,-0.22663,-1.93633]},"J6o":{"weight":1.0,"played":[1.0,0.0,0.0],"evs":[0.0,-0.26528,-2.07101]},"Q6o":{"weight":1.0,"played":[1.0,0.0,0.0],"evs":[0.0,-0.27686,-2.05801]},"K6o":{"weight":1.0,"played":[1.0,0.0,0.0],"evs":[0.0,-0.14586,-1.8777]},"A6o":{"weight":1.0,"played":[1.0,0.0,0.0],"evs":[0.0,-0.12545,-1.43818]},"72s":{"weight":1.0,"played":[1.0,0.0,0.0],"evs":[0.0,-0.18311,-1.73935]},"73s":{"weight":1.0,"played":[1.0,0.0,0.0],"evs":[0.0,-0.15183,-1.58248]},"74s":{"weight":1.0,"played":[1.0,0.0,0.0],"evs":[0.0,-0.10411,-1.40944]},"75s":{"weight":1.0,"played":[1.0,0.0,0.0],"evs":[0.0,-0.06993,-1.24678]},"76s":{"weight":1.0,"played":[0.9998,2.0E-4,0.0],"evs":[0.0,-0.01199,-1.08211]},"77":{"weight":1.0,"played":[0.9999,1.0E-4,0.0],"evs":[0.0,-0.02442,-0.71551]},"87o":{"weight":1.0,"played":[1.0,0.0,0.0],"evs":[0.0,-0.10738,-1.53625]},"97o":{"weight":1.0,"played":[1.0,0.0,0.0],"evs":[0.0,-0.14281,-1.69439]},"T7o":{"weight":1.0,"played":[1.0,0.0,0.0],"evs":[0.0,-0.19725,-1.83297]},"J7o":{"weight":1.0,"played":[1.0,0.0,0.0],"evs":[0.0,-0.23599,-1.96986]},"Q7o":{"weight":1.0,"played":[1.0,0.0,0.0],"evs":[0.0,-0.28953,-2.12303]},"K7o":{"weight":1.0,"played":[1.0,0.0,0.0],"evs":[0.0,-0.15845,-1.90628]},"A7o":{"weight":1.0,"played":[1.0,0.0,0.0],"evs":[0.0,-0.12707,-1.42931]},"82s":{"weight":1.0,"played":[1.0,0.0,0.0],"evs":[0.0,-0.16739,-1.69348]},"83s":{"weight":1.0,"played":[1.0,0.0,0.0],"evs":[0.0,-0.17745,-1.7096]},"84s":{"weight":1.0,"played":[1.0,0.0,0.0],"evs":[0.0,-0.13562,-1.53796]},"85s":{"weight":1.0,"played":[1.0,0.0,0.0],"evs":[0.0,-0.09132,-1.38831]},"86s":{"weight":1.0,"played":[1.0,0.0,0.0],"evs":[0.0,-0.03857,-1.22391]},"87s":{"weight":1.0,"played":[1.0,0.0,0.0],"evs":[0.0,-0.01475,-1.13214]},"88":{"weight":1.0,"played":[0.9786,0.0214,0.0],"evs":[0.0,-0.00974,-0.69325]},"98o":{"weight":1.0,"played":[1.0,0.0,0.0],"evs":[0.0,-0.12486,-1.62003]},"T8o":{"weight":1.0,"played":[1.0,0.0,0.0],"evs":[0.0,-0.16187,-1.69486]},"J8o":{"weight":1.0,"played":[1.0,0.0,0.0],"evs":[0.0,-0.20172,-1.82811]},"Q8o":{"weight":1.0,"played":[1.0,0.0,0.0],"evs":[0.0,-0.25722,-1.98964]},"K8o":{"weight":1.0,"played":[1.0,0.0,0.0],"evs":[0.0,-0.15834,-1.917]},"A8o":{"weight":1.0,"played":[1.0,0.0,0.0],"evs":[0.0,-0.12553,-1.43471]},"92s":{"weight":1.0,"played":[1.0,0.0,0.0],"evs":[0.0,-0.17201,-1.72305]},"93s":{"weight":1.0,"played":[1.0,0.0,0.0],"evs":[0.0,-0.17195,-1.70075]},"94s":{"weight":1.0,"played":[1.0,0.0,0.0],"evs":[0.0,-0.16755,-1.68185]},"95s":{"weight":1.0,"played":[1.0,0.0,0.0],"evs":[0.0,-0.12909,-1.5327]},"96s":{"weight":1.0,"played":[1.0,0.0,0.0],"evs":[0.0,-0.07383,-1.3819]},"97s":{"weight":1.0,"played":[1.0,0.0,0.0],"evs":[0.0,-0.04843,-1.28685]},"98s":{"weight":1.0,"played":[1.0,0.0,0.0],"evs":[0.0,-0.0322,-1.21762]},"99":{"weight":1.0,"played":[1.0,0.0,0.0],"evs":[0.0,-0.02932,-0.72159]},"T9o":{"weight":1.0,"played":[1.0,0.0,0.0],"evs":[0.0,-0.13856,-1.61473]},"J9o":{"weight":1.0,"played":[1.0,0.0,0.0],"evs":[0.0,-0.18949,-1.74949]},"Q9o":{"weight":1.0,"played":[1.0,0.0,0.0],"evs":[0.0,-0.24371,-1.89744]},"K9o":{"weight":1.0,"played":[1.0,0.0,0.0],"evs":[0.0,-0.14333,-1.86614]},"A9o":{"weight":1.0,"played":[1.0,0.0,0.0],"evs":[0.0,-0.12065,-1.46193]},"T2s":{"weight":1.0,"played":[1.0,0.0,0.0],"evs":[0.0,-0.1817,-1.7184]},"T3s":{"weight":1.0,"played":[1.0,0.0,0.0],"evs":[0.0,-0.18962,-1.70446]},"T4s":{"weight":1.0,"played":[1.0,0.0,0.0],"evs":[0.0,-0.18055,-1.66355]},"T5s":{"weight":1.0,"played":[1.0,0.0,0.0],"evs":[0.0,-0.18005,-1.66883]},"T6s":{"weight":1.0,"played":[1.0,0.0,0.0],"evs":[0.0,-0.12826,-1.50505]},"T7s":{"weight":1.0,"played":[1.0,0.0,0.0],"evs":[0.0,-0.10215,-1.41516]},"T8s":{"weight":1.0,"played":[1.0,0.0,0.0],"evs":[0.0,-0.06883,-1.28639]},"T9s":{"weight":1.0,"played":[1.0,0.0,0.0],"evs":[0.0,-0.03984,-1.19988]},"TT":{"weight":1.0,"played":[0.9489,0.0511,0.0],"evs":[0.0,-0.00743,-0.62456]},"JTo":{"weight":1.0,"played":[1.0,0.0,0.0],"evs":[0.0,-0.18123,-1.66905]},"QTo":{"weight":1.0,"played":[1.0,0.0,0.0],"evs":[0.0,-0.23885,-1.82049]},"KTo":{"weight":1.0,"played":[1.0,0.0,0.0],"evs":[0.0,-0.13807,-1.75696]},"ATo":{"weight":1.0,"played":[1.0,0.0,0.0],"evs":[0.0,-0.11936,-1.38724]},"J2s":{"weight":1.0,"played":[1.0,0.0,0.0],"evs":[0.0,-0.18446,-1.73486]},"J3s":{"weight":1.0,"played":[1.0,0.0,0.0],"evs":[0.0,-0.19213,-1.71919]},"J4s":{"weight":1.0,"played":[1.0,0.0,0.0],"evs":[0.0,-0.18246,-1.66471]},"J5s":{"weight":1.0,"played":[1.0,0.0,0.0],"evs":[0.0,-0.17389,-1.63206]},"J6s":{"weight":1.0,"played":[1.0,0.0,0.0],"evs":[0.0,-0.16005,-1.6404]},"J7s":{"weight":1.0,"played":[1.0,0.0,0.0],"evs":[0.0,-0.13376,-1.53684]},"J8s":{"weight":1.0,"played":[1.0,0.0,0.0],"evs":[0.0,-0.10047,-1.40904]},"J9s":{"weight":1.0,"played":[1.0,0.0,0.0],"evs":[0.0,-0.08828,-1.32927]},"JTs":{"weight":1.0,"played":[1.0,0.0,0.0],"evs":[0.0,-0.08089,-1.24462]},"JJ":{"weight":1.0,"played":[0.9975,0.0025,0.0],"evs":[0.0,-0.00751,-0.46531]},"QJo":{"weight":1.0,"played":[1.0,0.0,0.0],"evs":[0.0,-0.2396,-1.83339]},"KJo":{"weight":1.0,"played":[1.0,0.0,0.0],"evs":[0.0,-0.12654,-1.75139]},"AJo":{"weight":1.0,"played":[1.0,0.0,0.0],"evs":[0.0,-0.11224,-1.37246]},"Q2s":{"weight":1.0,"played":[1.0,0.0,0.0],"evs":[0.0,-0.20367,-1.75674]},"Q3s":{"weight":1.0,"played":[1.0,0.0,0.0],"evs":[0.0,-0.20944,-1.73626]},"Q4s":{"weight":1.0,"played":[1.0,0.0,0.0],"evs":[0.0,-0.19562,-1.69115]},"Q5s":{"weight":1.0,"played":[1.0,0.0,0.0],"evs":[0.0,-0.18933,-1.65047]},"Q6s":{"weight":1.0,"played":[1.0,0.0,0.0],"evs":[0.0,-0.16836,-1.61722]},"Q7s":{"weight":1.0,"played":[1.0,0.0,0.0],"evs":[0.0,-0.18427,-1.68797]},"Q8s":{"weight":1.0,"played":[1.0,0.0,0.0],"evs":[0.0,-0.14739,-1.55342]},"Q9s":{"weight":1.0,"played":[1.0,0.0,0.0],"evs":[0.0,-0.13593,-1.46942]},"QTs":{"weight":1.0,"played":[1.0,0.0,0.0],"evs":[0.0,-0.13282,-1.38745]},"QJs":{"weight":1.0,"played":[1.0,0.0,0.0],"evs":[0.0,-0.1352,-1.4041]},"QQ":{"weight":1.0,"played":[0.775,0.225,0.0],"evs":[0.0,-0.00376,-0.26324]},"KQo":{"weight":1.0,"played":[1.0,0.0,0.0],"evs":[0.0,-0.13643,-1.75122]},"AQo":{"weight":1.0,"played":[1.0,0.0,0.0],"evs":[0.0,-0.1104,-1.37725]},"K2s":{"weight":1.0,"played":[1.0,0.0,0.0],"evs":[0.0,-0.06603,-1.60005]},"K3s":{"weight":1.0,"played":[1.0,0.0,0.0],"evs":[0.0,-0.06446,-1.5839]},"K4s":{"weight":1.0,"played":[1.0,0.0,0.0],"evs":[0.0,-0.04904,-1.52413]},"K5s":{"weight":1.0,"played":[1.0,0.0,0.0],"evs":[0.0,-0.04281,-1.49324]},"K6s":{"weight":1.0,"played":[0.9997,3.0E-4,0.0],"evs":[0.0,-0.0232,-1.44743]},"K7s":{"weight":1.0,"played":[1.0,0.0,0.0],"evs":[0.0,-0.03119,-1.48478]},"K8s":{"weight":1.0,"played":[1.0,0.0,0.0],"evs":[0.0,-0.02933,-1.47685]},"K9s":{"weight":1.0,"played":[1.0,0.0,0.0],"evs":[0.0,-0.0166,-1.4232]},"KTs":{"weight":1.0,"played":[0.7318,0.2682,0.0],"evs":[0.0,-7.0E-4,-1.29966]},"KJs":{"weight":1.0,"played":[0.993,0.007,0.0],"evs":[0.0,-0.01086,-1.34231]},"KQs":{"weight":1.0,"played":[1.0,0.0,0.0],"evs":[0.0,-0.0143,-1.33813]},"KK":{"weight":1.0,"played":[0.0,0.9912,0.0088],"evs":[0.0,0.96801,0.92941]},"AKo":{"weight":1.0,"played":[0.2374,0.7626,0.0],"evs":[0.0,-2.3E-4,-0.13451]},"A2s":{"weight":1.0,"played":[1.0,0.0,0.0],"evs":[0.0,-0.01892,-0.974]},"A3s":{"weight":1.0,"played":[0.997,0.003,0.0],"evs":[0.0,-0.00811,-0.93097]},"A4s":{"weight":1.0,"played":[0.8114,0.1886,0.0],"evs":[0.0,-0.0027,-0.91182]},"A5s":{"weight":1.0,"played":[0.6053,0.3947,0.0],"evs":[0.0,0.0,-0.88193]},"A6s":{"weight":1.0,"played":[1.0,0.0,0.0],"evs":[0.0,-0.01734,-1.01421]},"A7s":{"weight":1.0,"played":[0.9571,0.0429,0.0],"evs":[0.0,-0.00584,-1.00171]},"A8s":{"weight":1.0,"played":[0.7994,0.2006,0.0],"evs":[0.0,-5.0E-4,-1.0033]},"A9s":{"weight":1.0,"played":[0.9999,1.0E-4,0.0],"evs":[0.0,-0.00502,-1.03572]},"ATs":{"weight":1.0,"played":[0.7702,0.2298,0.0],"evs":[0.0,-0.00131,-0.97154]},"AJs":{"weight":1.0,"played":[0.595,0.405,0.0],"evs":[0.0,-3.7E-4,-0.95585]},"AQs":{"weight":1.0,"played":[0.9998,2.0E-4,0.0],"evs":[0.0,-0.00407,-0.96854]},"AKs":{"weight":1.0,"played":[0.0,0.9764,0.0236],"evs":[0.0,0.17647,0.1681]},"AA":{"weight":1.0,"played":[0.0,1.0,0.0],"evs":[0.0,3.97227,3.9246]}}}