{"player":4,"street":0,"children":2,"sequence":[{"player":0,"type":"R","amount":250000,"street":0},{"player":1,"type":"F","amount":0,"street":0},{"player":2,"type":"F","amount":0,"street":0},{"player":3,"type":"F","amount":0,"street":0},{"player":4,"type":"R","amount":1000000,"street":0},{"player":5,"type":"F","amount":0,"street":0},{"player":6,"type":"F","amount":0,"street":0},{"player":7,"type":"R","amount":2500000,"street":0},{"player":0,"type":"R","amount":10000000,"street":0}],"actions":[{"type":"F","amount":0,"node":755},{"type":"C","amount":9000000}],"hands":{"22":{"weight":0.0,"played":[1.0,0.0],"evs":[0.0,-2.02966]},"32o":{"weight":0.0,"played":[1.0,0.0],"evs":[0.0,-4.92722]},"42o":{"weight":0.0,"played":[1.0,0.0],"evs":[0.0,-4.84487]},"52o":{"weight":0.0,"played":[1.0,0.0],"evs":[0.0,-4.62297]},"62o":{"weight":0.0,"played":[1.0,0.0],"evs":[0.0,-4.86748]},"72o":{"weight":0.0,"played":[1.0,0.0],"evs":[0.0,-5.25459]},"82o":{"weight":0.0,"played":[1.0,0.0],"evs":[0.0,-5.16495]},"92o":{"weight":0.0,"played":[1.0,0.0],"evs":[0.0,-5.35647]},"T2o":{"weight":0.0,"played":[1.0,0.0],"evs":[0.0,-5.37079]},"J2o":{"weight":0.0,"played":[1.0,0.0],"evs":[0.0,-5.5083]},"Q2o":{"weight":0.0,"played":[1.0,0.0],"evs":[0.0,-5.73759]},"K2o":{"weight":0.0,"played":[1.0,0.0],"evs":[0.0,-7.4659]},"A2o":{"weight":0.0,"played":[1.0,0.0],"evs":[0.0,-5.2398]},"32s":{"weight":0.0,"played":[1.0,0.0],"evs":[0.0,-3.77101]},"33":{"weight":0.0,"played":[1.0,0.0],"evs":[0.0,-1.8649]},"43o":{"weight":0.0,"played":[1.0,0.0],"evs":[0.0,-4.2708]},"53o":{"weight":0.0,"played":[1.0,0.0],"evs":[0.0,-4.17411]},"63o":{"weight":0.0,"played":[1.0,0.0],"evs":[0.0,-4.35888]},"73o":{"weight":0.0,"played":[1.0,0.0],"evs":[0.0,-4.76369]},"83o":{"weight":0.0,"played":[1.0,0.0],"evs":[0.0,-5.21563]},"93o":{"weight":0.0,"played":[1.0,0.0],"evs":[0.0,-5.16492]},"T3o":{"weight":0.0,"played":[1.0,0.0],"evs":[0.0,-5.24063]},"J3o":{"weight":0.0,"played":[1.0,0.0],"evs":[0.0,-5.43928]},"Q3o":{"weight":0.0,"played":[1.0,0.0],"evs":[0.0,-5.53785]},"K3o":{"weight":0.0,"played":[1.0,0.0],"evs":[0.0,-7.28586]},"A3o":{"weight":0.0,"played":[1.0,0.0],"evs":[0.0,-5.17831]},"42s":{"weight":0.0,"played":[1.0,0.0],"evs":[0.0,-3.64975]},"43s":{"weight":0.0,"played":[1.0,0.0],"evs":[0.0,-3.17667]},"44":{"weight":0.0379,"played":[1.0,0.0],"evs":[0.0,-1.54925]},"54o":{"weight":0.0,"played":[1.0,0.0],"evs":[0.0,-3.71331]},"64o":{"weight":0.0,"played":[1.0,0.0],"evs":[0.0,-3.89891]},"74o":{"weight":0.0,"played":[1.0,0.0],"evs":[0.0,-4.39014]},"84o":{"weight":0.0,"played":[1.0,0.0],"evs":[0.0,-4.74784]},"94o":{"weight":0.0,"played":[1.0,0.0],"evs":[0.0,-5.18537]},"T4o":{"weight":0.0,"played":[1.0,0.0],"evs":[0.0,-5.11801]},"J4o":{"weight":0.0,"played":[1.0,0.0],"evs":[0.0,-5.25068]},"Q4o":{"weight":0.0,"played":[1.0,0.0],"evs":[0.0,-5.48526]},"K4o":{"weight":0.0,"played":[1.0,0.0],"evs":[0.0,-7.27867]},"A4o":{"weight":0.0,"played":[1.0,0.0],"evs":[0.0,-4.96071]},"52s":{"weight":0.0,"played":[1.0,0.0],"evs":[0.0,-3.54797]},"53s":{"weight":0.0,"played":[1.0,0.0],"evs":[0.0,-3.28474]},"54s":{"weight":0.176,"played":[1.0,0.0],"evs":[0.0,-2.79227]},"55":{"weight":0.0588,"played":[1.0,0.0],"evs":[0.0,-1.49075]},"65o":{"weight":0.0,"played":[1.0,0.0],"evs":[0.0,-3.38136]},"75o":{"weight":0.0,"played":[1.0,0.0],"evs":[0.0,-3.83429]},"85o":{"weight":0.0,"played":[1.0,0.0],"evs":[0.0,-4.26245]},"95o":{"weight":0.0,"played":[1.0,0.0],"evs":[0.0,-4.69153]},"T5o":{"weight":0.0,"played":[1.0,0.0],"evs":[0.0,-5.10956]},"J5o":{"weight":0.0,"played":[1.0,0.0],"evs":[0.0,-5.07262]},"Q5o":{"weight":0.0,"played":[1.0,0.0],"evs":[0.0,-5.21574]},"K5o":{"weight":0.0,"played":[1.0,0.0],"evs":[0.0,-7.06777]},"A5o":{"weight":0.0,"played":[1.0,0.0],"evs":[0.0,-4.78305]},"62s":{"weight":0.0,"played":[1.0,0.0],"evs":[0.0,-3.81462]},"63s":{"weight":0.0,"played":[1.0,0.0],"evs":[0.0,-3.38493]},"64s":{"weight":0.0,"played":[1.0,0.0],"evs":[0.0,-2.87368]},"65s":{"weight":0.1509,"played":[1.0,0.0],"evs":[0.0,-2.30938]},"66":{"weight":0.1119,"played":[1.0,0.0],"evs":[0.0,-1.33279]},"76o":{"weight":0.0,"played":[1.0,0.0],"evs":[0.0,-3.37209]},"86o":{"weight":0.0,"played":[1.0,0.0],"evs":[0.0,-3.85124]},"96o":{"weight":0.0,"played":[1.0,0.0],"evs":[0.0,-4.17566]},"T6o":{"weight":0.0,"played":[1.0,0.0],"evs":[0.0,-4.70812]},"J6o":{"weight":0.0,"played":[1.0,0.0],"evs":[0.0,-5.14304]},"Q6o":{"weight":0.0,"played":[1.0,0.0],"evs":[0.0,-5.18374]},"K6o":{"weight":0.0,"played":[1.0,0.0],"evs":[0.0,-6.88507]},"A6o":{"weight":0.0,"played":[1.0,0.0],"evs":[0.0,-5.2054]},"72s":{"weight":0.0,"played":[1.0,0.0],"evs":[0.0,-4.18112]},"73s":{"weight":0.0,"played":[1.0,0.0],"evs":[0.0,-3.71885]},"74s":{"weight":0.0,"played":[1.0,0.0],"evs":[0.0,-3.18012]},"75s":{"weight":0.0,"played":[1.0,0.0],"evs":[0.0,-2.76282]},"76s":{"weight":0.2099,"played":[1.0,0.0],"evs":[0.0,-2.27399]},"77":{"weight":0.0638,"played":[1.0,0.0],"evs":[0.0,-1.38004]},"87o":{"weight":0.0,"played":[1.0,0.0],"evs":[0.0,-3.51329]},"97o":{"weight":0.0,"played":[1.0,0.0],"evs":[0.0,-3.86423]},"T7o":{"weight":0.0,"played":[1.0,0.0],"evs":[0.0,-4.26125]},"J7o":{"weight":0.0,"played":[1.0,0.0],"evs":[0.0,-4.71772]},"Q7o":{"weight":0.0,"played":[1.0,0.0],"evs":[0.0,-5.31545]},"K7o":{"weight":0.0,"played":[1.0,0.0],"evs":[0.0,-6.85031]},"A7o":{"weight":0.0,"played":[1.0,0.0],"evs":[0.0,-5.1379]},"82s":{"weight":0.0,"played":[1.0,0.0],"evs":[0.0,-4.07949]},"83s":{"weight":0.0,"played":[1.0,0.0],"evs":[0.0,-4.16285]},"84s":{"weight":0.0,"played":[1.0,0.0],"evs":[0.0,-3.70446]},"85s":{"weight":0.0,"played":[1.0,0.0],"evs":[0.0,-3.17771]},"86s":{"weight":0.0,"played":[1.0,0.0],"evs":[0.0,-2.78759]},"87s":{"weight":0.2411,"played":[1.0,0.0],"evs":[0.0,-2.37958]},"88":{"weight":0.0056,"played":[1.0,0.0],"evs":[0.0,-1.26644]},"98o":{"weight":0.0,"played":[1.0,0.0],"evs":[0.0,-3.73391]},"T8o":{"weight":0.0,"played":[1.0,0.0],"evs":[0.0,-3.92314]},"J8o":{"weight":0.0,"played":[1.0,0.0],"evs":[0.0,-4.38348]},"Q8o":{"weight":0.0,"played":[1.0,0.0],"evs":[0.0,-4.99976]},"K8o":{"weight":0.0,"played":[1.0,0.0],"evs":[0.0,-6.93578]},"A8o":{"weight":0.0,"played":[1.0,0.0],"evs":[0.0,-5.27621]},"92s":{"weight":0.0,"played":[1.0,0.0],"evs":[0.0,-4.29072]},"93s":{"weight":0.0,"played":[1.0,0.0],"evs":[0.0,-4.0319]},"94s":{"weight":0.0,"played":[1.0,0.0],"evs":[0.0,-4.03672]},"95s":{"weight":0.0,"played":[1.0,0.0],"evs":[0.0,-3.62858]},"96s":{"weight":0.0,"played":[1.0,0.0],"evs":[0.0,-3.14457]},"97s":{"weight":0.0,"played":[1.0,0.0],"evs":[0.0,-2.74855]},"98s":{"weight":0.0152,"played":[1.0,0.0],"evs":[0.0,-2.72725]},"99":{"weight":0.0145,"played":[1.0,0.0],"evs":[0.0,-1.3911]},"T9o":{"weight":0.0,"played":[1.0,0.0],"evs":[0.0,-3.71521]},"J9o":{"weight":0.0,"played":[1.0,0.0],"evs":[0.0,-4.22788]},"Q9o":{"weight":0.0,"played":[1.0,0.0],"evs":[0.0,-4.73932]},"K9o":{"weight":0.0,"played":[1.0,0.0],"evs":[0.0,-6.85943]},"A9o":{"weight":0.0,"played":[1.0,0.0],"evs":[0.0,-5.29381]},"T2s":{"weight":0.0,"played":[1.0,0.0],"evs":[0.0,-4.23976]},"T3s":{"weight":0.0,"played":[1.0,0.0],"evs":[0.0,-4.24345]},"T4s":{"weight":0.0,"played":[1.0,0.0],"evs":[0.0,-3.99505]},"T5s":{"weight":0.0,"played":[1.0,0.0],"evs":[0.0,-3.94861]},"T6s":{"weight":0.0,"played":[1.0,0.0],"evs":[0.0,-3.55765]},"T7s":{"weight":0.0,"played":[1.0,0.0],"evs":[0.0,-3.32914]},"T8s":{"weight":0.2822,"played":[1.0,0.0],"evs":[0.0,-2.8286]},"T9s":{"weight":0.2107,"played":[1.0,0.0],"evs":[0.0,-2.76791]},"TT":{"weight":0.146,"played":[1.0,0.0],"evs":[0.0,-1.17132]},"JTo":{"weight":0.0,"played":[1.0,0.0],"evs":[0.0,-4.20326]},"QTo":{"weight":0.0,"played":[1.0,0.0],"evs":[0.0,-4.69935]},"KTo":{"weight":0.1135,"played":[1.0,0.0],"evs":[0.0,-6.548]},"ATo":{"weight":0.1061,"played":[1.0,0.0],"evs":[0.0,-5.25968]},"J2s":{"weight":0.0,"played":[1.0,0.0],"evs":[0.0,-4.38787]},"J3s":{"weight":0.0,"played":[1.0,0.0],"evs":[0.0,-4.24747]},"J4s":{"weight":0.0,"played":[1.0,0.0],"evs":[0.0,-4.12081]},"J5s":{"weight":0.0,"played":[1.0,0.0],"evs":[0.0,-4.11501]},"J6s":{"weight":0.0,"played":[1.0,0.0],"evs":[0.0,-3.95584]},"J7s":{"weight":0.0,"played":[1.0,0.0],"evs":[0.0,-3.63425]},"J8s":{"weight":0.0,"played":[1.0,0.0],"evs":[0.0,-3.38043]},"J9s":{"weight":0.0889,"played":[1.0,0.0],"evs":[0.0,-3.14935]},"JTs":{"weight":0.0994,"played":[1.0,0.0],"evs":[0.0,-3.03933]},"JJ":{"weight":0.1651,"played":[1.0,0.0],"evs":[0.0,-1.28941]},"QJo":{"weight":0.0,"played":[1.0,0.0],"evs":[0.0,-4.79685]},"KJo":{"weight":0.0691,"played":[1.0,0.0],"evs":[0.0,-6.69586]},"AJo":{"weight":0.2468,"played":[1.0,0.0],"evs":[0.0,-5.35675]},"Q2s":{"weight":0.0,"played":[1.0,0.0],"evs":[0.0,-4.59789]},"Q3s":{"weight":0.0,"played":[1.0,0.0],"evs":[0.0,-4.35357]},"Q4s":{"weight":0.0,"played":[1.0,0.0],"evs":[0.0,-4.38258]},"Q5s":{"weight":0.0,"played":[1.0,0.0],"evs":[0.0,-4.20793]},"Q6s":{"weight":0.0,"played":[1.0,0.0],"evs":[0.0,-4.0251]},"Q7s":{"weight":0.0,"played":[1.0,0.0],"evs":[0.0,-4.11209]},"Q8s":{"weight":0.0,"played":[1.0,0.0],"evs":[0.0,-3.9323]},"Q9s":{"weight":0.1242,"played":[1.0,0.0],"evs":[0.0,-3.74821]},"QTs":{"weight":0.0118,"played":[1.0,0.0],"evs":[0.0,-3.56923]},"QJs":{"weight":0.1718,"played":[1.0,0.0],"evs":[0.0,-3.62672]},"QQ":{"weight":0.193,"played":[1.0,0.0],"evs":[0.0,-1.4174]},"KQo":{"weight":0.381,"played":[1.0,0.0],"evs":[0.0,-6.89691]},"AQo":{"weight":0.0726,"played":[1.0,0.0],"evs":[0.0,-5.66998]},"K2s":{"weight":0.0,"played":[1.0,0.0],"evs":[0.0,-6.17628]},"K3s":{"weight":1.0E-4,"played":[1.0,0.0],"evs":[0.0,-5.98257]},"K4s":{"weight":0.1213,"played":[1.0,0.0],"evs":[0.0,-5.73258]},"K5s":{"weight":0.3639,"played":[1.0,0.0],"evs":[0.0,-5.76397]},"K6s":{"weight":0.0,"played":[1.0,0.0],"evs":[0.0,-5.48385]},"K7s":{"weight":0.2472,"played":[1.0,0.0],"evs":[0.0,-5.5327]},"K8s":{"weight":0.2666,"played":[1.0,0.0],"evs":[0.0,-5.72196]},"K9s":{"weight":0.2931,"played":[1.0,0.0],"evs":[0.0,-5.51157]},"KTs":{"weight":3.0E-4,"played":[1.0,0.0],"evs":[0.0,-5.13493]},"KJs":{"weight":0.064,"played":[1.0,0.0],"evs":[0.0,-5.35255]},"KQs":{"weight":0.1494,"played":[1.0,0.0],"evs":[0.0,-5.46663]},"KK":{"weight":0.7162,"played":[0.9999,1.0E-4],"evs":[0.0,-2.25552]},"AKo":{"weight":0.4576,"played":[1.0,0.0],"evs":[0.0,-3.11638]},"A2s":{"weight":0.7047,"played":[1.0,0.0],"evs":[0.0,-4.08057]},"A3s":{"weight":0.753,"played":[1.0,0.0],"evs":[0.0,-3.85316]},"A4s":{"weight":0.2943,"played":[1.0,0.0],"evs":[0.0,-3.81618]},"A5s":{"weight":0.103,"played":[1.0,0.0],"evs":[0.0,-3.57191]},"A6s":{"weight":0.4263,"played":[1.0,0.0],"evs":[0.0,-4.04893]},"A7s":{"weight":0.2877,"played":[1.0,0.0],"evs":[0.0,-3.89585]},"A8s":{"weight":0.1965,"played":[1.0,0.0],"evs":[0.0,-3.97725]},"A9s":{"weight":0.0075,"played":[1.0,0.0],"evs":[0.0,-4.00984]},"ATs":{"weight":0.1642,"played":[1.0,0.0],"evs":[0.0,-4.02909]},"AJs":{"weight":0.3589,"played":[1.0,0.0],"evs":[0.0,-4.1583]},"AQs":{"weight":0.0894,"played":[1.0,0.0],"evs":[0.0,-4.48997]},"AKs":{"weight":0.9981,"played":[1.0,0.0],"evs":[0.0,-1.78895]},"AA":{"weight":1.0,"played":[0.0,1.0],"evs":[0.0,11.4552]}}}