{"player":3,"street":0,"children":3,"sequence":[{"player":0,"type":"F","amount":0,"street":0},{"player":1,"type":"F","amount":0,"street":0},{"player":2,"type":"R","amount":200000,"street":0},{"player":3,"type":"R","amount":500000,"street":0},{"player":4,"type":"F","amount":0,"street":0},{"player":5,"type":"F","amount":0,"street":0},{"player":6,"type":"R","amount":1487500,"street":0},{"player":2,"type":"C","amount":1287500,"street":0}],"actions":[{"type":"F","amount":0},{"type":"C","amount":987500},{"type":"R","amount":2287500,"node":429}],"hands":{"22":{"weight":0.0,"played":[1.0,0.0,0.0],"evs":[0.0,-0.96388,-0.88]},"32o":{"weight":0.0,"played":[1.0,0.0,0.0],"evs":[0.0,-1.55099,-1.86871]},"42o":{"weight":0.0,"played":[1.0,0.0,0.0],"evs":[0.0,-1.5148,-1.81891]},"52o":{"weight":0.0,"played":[1.0,0.0,0.0],"evs":[0.0,-1.4645,-1.74296]},"62o":{"weight":0.0,"played":[1.0,0.0,0.0],"evs":[0.0,-1.53728,-1.823]},"72o":{"weight":0.0,"played":[1.0,0.0,0.0],"evs":[0.0,-1.69999,-2.06362]},"82o":{"weight":0.0,"played":[1.0,0.0,0.0],"evs":[0.0,-1.67506,-2.021]},"92o":{"weight":0.0,"played":[1.0,0.0,0.0],"evs":[0.0,-1.69458,-2.01136]},"T2o":{"weight":0.0,"played":[1.0,0.0,0.0],"evs":[0.0,-1.66689,-1.94801]},"J2o":{"weight":0.0,"played":[1.0,0.0,0.0],"evs":[0.0,-1.88183,-2.53894]},"Q2o":{"weight":0.0,"played":[1.0,0.0,0.0],"evs":[0.0,-1.57036,-2.09733]},"K2o":{"weight":0.0,"played":[1.0,0.0,0.0],"evs":[0.0,-1.60181,-2.13724]},"A2o":{"weight":0.0,"played":[1.0,0.0,0.0],"evs":[0.0,-1.37579,-1.57033]},"32s":{"weight":0.0,"played":[1.0,0.0,0.0],"evs":[0.0,-1.20049,-1.36095]},"33":{"weight":0.0,"played":[1.0,0.0,0.0],"evs":[0.0,-0.93445,-0.81011]},"43o":{"weight":0.0,"played":[1.0,0.0,0.0],"evs":[0.0,-1.36366,-1.59993]},"53o":{"weight":0.0,"played":[1.0,0.0,0.0],"evs":[0.0,-1.30819,-1.53134]},"63o":{"weight":0.0,"played":[1.0,0.0,0.0],"evs":[0.0,-1.38552,-1.62066]},"73o":{"weight":0.0,"played":[1.0,0.0,0.0],"evs":[0.0,-1.55168,-1.83082]},"83o":{"weight":0.0,"played":[1.0,0.0,0.0],"evs":[0.0,-1.66184,-1.99687]},"93o":{"weight":0.0,"played":[1.0,0.0,0.0],"evs":[0.0,-1.64972,-1.94217]},"T3o":{"weight":0.0,"played":[1.0,0.0,0.0],"evs":[0.0,-1.63662,-1.8983]},"J3o":{"weight":0.0,"played":[1.0,0.0,0.0],"evs":[0.0,-1.86255,-2.49417]},"Q3o":{"weight":0.0,"played":[1.0,0.0,0.0],"evs":[0.0,-1.54366,-2.05744]},"K3o":{"weight":0.0,"played":[1.0,0.0,0.0],"evs":[0.0,-1.58428,-2.09991]},"A3o":{"weight":0.0,"played":[1.0,0.0,0.0],"evs":[0.0,-1.35771,-1.53104]},"42s":{"weight":0.0,"played":[1.0,0.0,0.0],"evs":[0.0,-1.19516,-1.36462]},"43s":{"weight":0.0,"played":[1.0,0.0,0.0],"evs":[0.0,-1.02139,-1.16683]},"44":{"weight":0.0,"played":[1.0,0.0,0.0],"evs":[0.0,-0.91959,-0.78749]},"54o":{"weight":0.0,"played":[1.0,0.0,0.0],"evs":[0.0,-1.16899,-1.30303]},"64o":{"weight":0.0,"played":[1.0,0.0,0.0],"evs":[0.0,-1.23247,-1.41137]},"74o":{"weight":0.0,"played":[1.0,0.0,0.0],"evs":[0.0,-1.39044,-1.61095]},"84o":{"weight":0.0,"played":[1.0,0.0,0.0],"evs":[0.0,-1.54313,-1.79709]},"94o":{"weight":0.0,"played":[1.0,0.0,0.0],"evs":[0.0,-1.64022,-1.93769]},"T4o":{"weight":0.0,"played":[1.0,0.0,0.0],"evs":[0.0,-1.60947,-1.84181]},"J4o":{"weight":0.0,"played":[1.0,0.0,0.0],"evs":[0.0,-1.81689,-2.42182]},"Q4o":{"weight":0.0,"played":[1.0,0.0,0.0],"evs":[0.0,-1.49567,-1.98334]},"K4o":{"weight":0.0,"played":[1.0,0.0,0.0],"evs":[0.0,-1.53816,-2.01834]},"A4o":{"weight":0.0,"played":[1.0,0.0,0.0],"evs":[0.0,-1.30737,-1.43544]},"52s":{"weight":0.0,"played":[1.0,0.0,0.0],"evs":[0.0,-1.12877,-1.28618]},"53s":{"weight":0.0,"played":[1.0,0.0,0.0],"evs":[0.0,-0.94519,-1.02503]},"54s":{"weight":0.0,"played":[1.0,0.0,0.0],"evs":[0.0,-0.78387,-0.84267]},"55":{"weight":0.0,"played":[1.0,0.0,0.0],"evs":[0.0,-0.89075,-0.70823]},"65o":{"weight":0.0,"played":[1.0,0.0,0.0],"evs":[0.0,-1.10315,-1.23205]},"75o":{"weight":0.0,"played":[1.0,0.0,0.0],"evs":[0.0,-1.2489,-1.42948]},"85o":{"weight":0.0,"played":[1.0,0.0,0.0],"evs":[0.0,-1.36149,-1.57233]},"95o":{"weight":0.0,"played":[1.0,0.0,0.0],"evs":[0.0,-1.51736,-1.76299]},"T5o":{"weight":0.0,"played":[1.0,0.0,0.0],"evs":[0.0,-1.60163,-1.85794]},"J5o":{"weight":0.0,"played":[1.0,0.0,0.0],"evs":[0.0,-1.79614,-2.39736]},"Q5o":{"weight":0.0,"played":[1.0,0.0,0.0],"evs":[0.0,-1.48049,-1.95094]},"K5o":{"weight":0.0,"played":[1.0,0.0,0.0],"evs":[0.0,-1.49462,-1.95043]},"A5o":{"weight":0.0,"played":[1.0,0.0,0.0],"evs":[0.0,-1.26349,-1.38433]},"62s":{"weight":0.0,"played":[1.0,0.0,0.0],"evs":[0.0,-1.18808,-1.33122]},"63s":{"weight":0.0,"played":[1.0,0.0,0.0],"evs":[0.0,-1.06674,-1.1716]},"64s":{"weight":0.0,"played":[1.0,0.0,0.0],"evs":[0.0,-0.86681,-0.94533]},"65s":{"weight":0.0,"played":[1.0,0.0,0.0],"evs":[0.0,-0.75351,-0.77981]},"66":{"weight":1.0E-4,"played":[1.0,0.0,0.0],"evs":[0.0,-0.86216,-0.6329]},"76o":{"weight":0.0,"played":[1.0,0.0,0.0],"evs":[0.0,-1.13857,-1.26415]},"86o":{"weight":0.0,"played":[1.0,0.0,0.0],"evs":[0.0,-1.24805,-1.42098]},"96o":{"weight":0.0,"played":[1.0,0.0,0.0],"evs":[0.0,-1.36797,-1.56579]},"T6o":{"weight":0.0,"played":[1.0,0.0,0.0],"evs":[0.0,-1.47318,-1.66425]},"J6o":{"weight":0.0,"played":[1.0,0.0,0.0],"evs":[0.0,-1.79245,-2.39744]},"Q6o":{"weight":0.0,"played":[1.0,0.0,0.0],"evs":[0.0,-1.43613,-1.88474]},"K6o":{"weight":0.0,"played":[1.0,0.0,0.0],"evs":[0.0,-1.48616,-1.94856]},"A6o":{"weight":0.0,"played":[1.0,0.0,0.0],"evs":[0.0,-1.37996,-1.591]},"72s":{"weight":0.0,"played":[1.0,0.0,0.0],"evs":[0.0,-1.33241,-1.56081]},"73s":{"weight":0.0,"played":[1.0,0.0,0.0],"evs":[0.0,-1.23059,-1.3759]},"74s":{"weight":0.0,"played":[1.0,0.0,0.0],"evs":[0.0,-1.06979,-1.16929]},"75s":{"weight":0.0,"played":[1.0,0.0,0.0],"evs":[0.0,-0.93703,-0.99899]},"76s":{"weight":0.0,"played":[1.0,0.0,0.0],"evs":[0.0,-0.78904,-0.82347]},"77":{"weight":0.0,"played":[1.0,0.0,0.0],"evs":[0.0,-0.83114,-0.65819]},"87o":{"weight":0.0,"played":[1.0,0.0,0.0],"evs":[0.0,-1.2088,-1.30377]},"97o":{"weight":0.0,"played":[1.0,0.0,0.0],"evs":[0.0,-1.3038,-1.43573]},"T7o":{"weight":0.0,"played":[1.0,0.0,0.0],"evs":[0.0,-1.38037,-1.52159]},"J7o":{"weight":0.0,"played":[1.0,0.0,0.0],"evs":[0.0,-1.70942,-2.2549]},"Q7o":{"weight":0.0,"played":[1.0,0.0,0.0],"evs":[0.0,-1.48186,-1.95487]},"K7o":{"weight":0.0,"played":[1.0,0.0,0.0],"evs":[0.0,-1.49135,-1.93989]},"A7o":{"weight":0.0,"played":[1.0,0.0,0.0],"evs":[0.0,-1.365,-1.53372]},"82s":{"weight":0.0,"played":[1.0,0.0,0.0],"evs":[0.0,-1.30618,-1.50063]},"83s":{"weight":0.0,"played":[1.0,0.0,0.0],"evs":[0.0,-1.29619,-1.50364]},"84s":{"weight":0.0,"played":[1.0,0.0,0.0],"evs":[0.0,-1.1714,-1.30296]},"85s":{"weight":0.0,"played":[1.0,0.0,0.0],"evs":[0.0,-1.01775,-1.11306]},"86s":{"weight":0.0,"played":[1.0,0.0,0.0],"evs":[0.0,-0.89408,-0.92957]},"87s":{"weight":0.0,"played":[1.0,0.0,0.0],"evs":[0.0,-0.83403,-0.83401]},"88":{"weight":0.7485,"played":[1.0,0.0,0.0],"evs":[0.0,-0.84822,-0.62414]},"98o":{"weight":0.0,"played":[1.0,0.0,0.0],"evs":[0.0,-1.30161,-1.39838]},"T8o":{"weight":0.0,"played":[1.0,0.0,0.0],"evs":[0.0,-1.31944,-1.42934]},"J8o":{"weight":0.0,"played":[1.0,0.0,0.0],"evs":[0.0,-1.61607,-2.10169]},"Q8o":{"weight":0.0,"played":[1.0,0.0,0.0],"evs":[0.0,-1.44003,-1.85695]},"K8o":{"weight":0.0,"played":[1.0,0.0,0.0],"evs":[0.0,-1.55217,-2.00822]},"A8o":{"weight":0.0513,"played":[1.0,0.0,0.0],"evs":[0.0,-1.39622,-1.54532]},"92s":{"weight":0.0,"played":[1.0,0.0,0.0],"evs":[0.0,-1.33994,-1.50884]},"93s":{"weight":0.0,"played":[1.0,0.0,0.0],"evs":[0.0,-1.27307,-1.4243]},"94s":{"weight":0.0,"played":[1.0,0.0,0.0],"evs":[0.0,-1.28255,-1.4315]},"95s":{"weight":0.0,"played":[1.0,0.0,0.0],"evs":[0.0,-1.16433,-1.2553]},"96s":{"weight":0.0,"played":[1.0,0.0,0.0],"evs":[0.0,-1.03344,-1.09171]},"97s":{"weight":0.0,"played":[1.0,0.0,0.0],"evs":[0.0,-1.00635,-1.02536]},"98s":{"weight":0.0,"played":[1.0,0.0,0.0],"evs":[0.0,-0.93539,-0.93]},"99":{"weight":1.0,"played":[1.0,0.0,0.0],"evs":[0.0,-0.73138,-0.42746]},"T9o":{"weight":0.0,"played":[1.0,0.0,0.0],"evs":[0.0,-1.25688,-1.2584]},"J9o":{"weight":0.0,"played":[1.0,0.0,0.0],"evs":[0.0,-1.56061,-1.96622]},"Q9o":{"weight":0.0,"played":[1.0,0.0,0.0],"evs":[0.0,-1.41365,-1.75933]},"K9o":{"weight":0.0,"played":[1.0,0.0,0.0],"evs":[0.0,-1.51813,-1.88551]},"A9o":{"weight":4.0E-4,"played":[1.0,0.0,0.0],"evs":[0.0,-1.40342,-1.55322]},"T2s":{"weight":0.0,"played":[1.0,0.0,0.0],"evs":[0.0,-1.36506,-1.5197]},"T3s":{"weight":0.0,"played":[1.0,0.0,0.0],"evs":[0.0,-1.28217,-1.38254]},"T4s":{"weight":0.0,"played":[1.0,0.0,0.0],"evs":[0.0,-1.23264,-1.32004]},"T5s":{"weight":0.0,"played":[1.0,0.0,0.0],"evs":[0.0,-1.26496,-1.37296]},"T6s":{"weight":0.0,"played":[1.0,0.0,0.0],"evs":[0.0,-1.10161,-1.1636]},"T7s":{"weight":0.0,"played":[1.0,0.0,0.0],"evs":[0.0,-1.06602,-1.08819]},"T8s":{"weight":0.0,"played":[1.0,0.0,0.0],"evs":[0.0,-0.95297,-0.95067]},"T9s":{"weight":0.0,"played":[1.0,0.0,0.0],"evs":[0.0,-0.93474,-0.8789]},"TT":{"weight":1.0,"played":[0.9998,0.0,2.0E-4],"evs":[0.0,-0.55442,-0.12677]},"JTo":{"weight":0.0,"played":[1.0,0.0,0.0],"evs":[0.0,-1.48252,-1.83594]},"QTo":{"weight":0.0,"played":[1.0,0.0,0.0],"evs":[0.0,-1.32383,-1.56466]},"KTo":{"weight":0.475,"played":[1.0,0.0,0.0],"evs":[0.0,-1.42203,-1.73158]},"ATo":{"weight":0.099,"played":[1.0,0.0,0.0],"evs":[0.0,-1.35157,-1.37095]},"J2s":{"weight":0.0,"played":[1.0,0.0,0.0],"evs":[0.0,-1.54669,-2.03138]},"J3s":{"weight":0.0,"played":[1.0,0.0,0.0],"evs":[0.0,-1.48975,-1.9799]},"J4s":{"weight":0.0,"played":[1.0,0.0,0.0],"evs":[0.0,-1.45073,-1.89551]},"J5s":{"weight":0.0,"played":[1.0,0.0,0.0],"evs":[0.0,-1.4311,-1.87722]},"J6s":{"weight":0.0,"played":[1.0,0.0,0.0],"evs":[0.0,-1.4366,-1.90246]},"J7s":{"weight":0.0,"played":[1.0,0.0,0.0],"evs":[0.0,-1.35321,-1.7365]},"J8s":{"weight":0.0,"played":[1.0,0.0,0.0],"evs":[0.0,-1.24013,-1.58834]},"J9s":{"weight":0.0,"played":[1.0,0.0,0.0],"evs":[0.0,-1.17296,-1.42727]},"JTs":{"weight":0.0,"played":[1.0,0.0,0.0],"evs":[0.0,-1.06335,-1.30279]},"JJ":{"weight":1.0,"played":[1.0,0.0,0.0],"evs":[0.0,-0.94573,-1.29806]},"QJo":{"weight":0.1875,"played":[1.0,0.0,0.0],"evs":[0.0,-1.55394,-2.17562]},"KJo":{"weight":0.8937,"played":[1.0,0.0,0.0],"evs":[0.0,-1.7058,-2.44087]},"AJo":{"weight":1.0,"played":[1.0,0.0,0.0],"evs":[0.0,-1.69781,-2.21416]},"Q2s":{"weight":0.0,"played":[1.0,0.0,0.0],"evs":[0.0,-1.23081,-1.59544]},"Q3s":{"weight":0.0,"played":[1.0,0.0,0.0],"evs":[0.0,-1.20326,-1.56132]},"Q4s":{"weight":0.0,"played":[1.0,0.0,0.0],"evs":[0.0,-1.19073,-1.52918]},"Q5s":{"weight":0.0,"played":[1.0,0.0,0.0],"evs":[0.0,-1.10808,-1.45032]},"Q6s":{"weight":0.0,"played":[1.0,0.0,0.0],"evs":[0.0,-1.08189,-1.43508]},"Q7s":{"weight":0.0,"played":[1.0,0.0,0.0],"evs":[0.0,-1.11071,-1.44765]},"Q8s":{"weight":0.3116,"played":[1.0,0.0,0.0],"evs":[0.0,-1.0947,-1.35955]},"Q9s":{"weight":0.9878,"played":[1.0,0.0,0.0],"evs":[0.0,-1.01234,-1.24055]},"QTs":{"weight":1.0,"played":[1.0,0.0,0.0],"evs":[0.0,-0.94916,-1.08807]},"QJs":{"weight":1.0,"played":[1.0,0.0,0.0],"evs":[0.0,-1.12124,-1.61109]},"QQ":{"weight":1.0,"played":[0.0773,0.026,0.8967],"evs":[0.0,0.12085,0.15818]},"KQo":{"weight":1.0,"played":[1.0,0.0,0.0],"evs":[0.0,-1.32289,-1.84767]},"AQo":{"weight":1.0,"played":[1.0,0.0,0.0],"evs":[0.0,-0.89066,-0.94261]},"K2s":{"weight":0.0,"played":[1.0,0.0,0.0],"evs":[0.0,-1.25258,-1.63164]},"K3s":{"weight":0.0,"played":[1.0,0.0,0.0],"evs":[0.0,-1.20847,-1.58371]},"K4s":{"weight":0.0,"played":[1.0,0.0,0.0],"evs":[0.0,-1.15654,-1.51618]},"K5s":{"weight":0.0,"played":[1.0,0.0,0.0],"evs":[0.0,-1.12037,-1.44889]},"K6s":{"weight":0.4661,"played":[1.0,0.0,0.0],"evs":[0.0,-1.10859,-1.43]},"K7s":{"weight":0.2569,"played":[1.0,0.0,0.0],"evs":[0.0,-1.14064,-1.44152]},"K8s":{"weight":0.9953,"played":[1.0,0.0,0.0],"evs":[0.0,-1.15676,-1.48084]},"K9s":{"weight":1.0,"played":[1.0,0.0,0.0],"evs":[0.0,-1.13929,-1.38617]},"KTs":{"weight":1.0,"played":[1.0,0.0,0.0],"evs":[0.0,-1.04076,-1.20908]},"KJs":{"weight":1.0,"played":[1.0,0.0,0.0],"evs":[0.0,-1.27942,-1.84307]},"KQs":{"weight":1.0,"played":[1.0,0.0,0.0],"evs":[0.0,-0.96659,-1.34799]},"KK":{"weight":1.0,"played":[0.0,0.0,1.0],"evs":[0.0,0.54128,0.63617]},"AKo":{"weight":1.0,"played":[0.6012,0.0,0.3988],"evs":[0.0,-0.37676,0.04711]},"A2s":{"weight":0.9367,"played":[1.0,0.0,0.0],"evs":[0.0,-0.9415,-1.00858]},"A3s":{"weight":1.0,"played":[1.0,0.0,0.0],"evs":[0.0,-0.93653,-0.95276]},"A4s":{"weight":0.999,"played":[1.0,0.0,0.0],"evs":[0.0,-0.86311,-0.87844]},"A5s":{"weight":0.0034,"played":[1.0,0.0,0.0],"evs":[0.0,-0.80851,-0.81991]},"A6s":{"weight":0.9998,"played":[1.0,0.0,0.0],"evs":[0.0,-0.98394,-1.06974]},"A7s":{"weight":1.0,"played":[1.0,0.0,0.0],"evs":[0.0,-0.97287,-1.0148]},"A8s":{"weight":1.0,"played":[1.0,0.0,0.0],"evs":[0.0,-1.00812,-1.06686]},"A9s":{"weight":1.0,"played":[1.0,0.0,0.0],"evs":[0.0,-0.99019,-0.99898]},"ATs":{"weight":0.9981,"played":[1.0,0.0,0.0],"evs":[0.0,-0.92255,-0.82277]},"AJs":{"weight":1.0,"played":[1.0,0.0,0.0],"evs":[0.0,-1.24731,-1.60369]},"AQs":{"weight":1.0,"played":[1.0,0.0,0.0],"evs":[0.0,-0.47847,-0.43699]},"AKs":{"weight":1.0,"played":[0.0,0.0,1.0],"evs":[0.0,-0.0046,0.44948]},"AA":{"weight":1.0,"played":[0.0,0.0,1.0],"evs":[0.0,4.75826,5.44277]}}}